refpapers/__init__.py
refpapers/apis.py
refpapers/conf.py
refpapers/doctypes.py
refpapers/filesystem.py
refpapers/git.py
refpapers/logger.py
refpapers/qualitycheck.py
refpapers/refpapers.py
refpapers/rename.py
refpapers/schema.py
refpapers/search.py
refpapers/utils.py
refpapers/view.py
refpapers-1.1.2.dist-info/entry_points.txt
refpapers-1.1.2.dist-info/LICENSE
refpapers-1.1.2.dist-info/WHEEL
refpapers-1.1.2.dist-info/METADATA
refpapers-1.1.2.dist-info/RECORD
