Metadata-Version: 2.1
Name: refpapers
Version: 1.1.2
Summary: refpapers - Manage and search bibliography from the command line
Author: Stig-Arne Grönroos
Author-email: stig.gronroos@gmail.com
Classifier: License :: OSI Approved :: MIT License
Classifier: Development Status :: 4 - Beta
Classifier: Intended Audience :: Science/Research
Classifier: Operating System :: OS Independent
Classifier: Programming Language :: Python
Classifier: Topic :: Scientific/Engineering
Requires-Dist: PyYAML==6.0.1
Requires-Dist: Unidecode==1.3.7
Requires-Dist: Whoosh==2.7.4
Requires-Dist: arxiv==2.0.0
Requires-Dist: bibtexparser==1.4.1
Requires-Dist: click==8.1.7
Requires-Dist: crossrefapi==1.6.0
Requires-Dist: delegator.py==0.1.1
Requires-Dist: prompt-toolkit==3.0.41
Requires-Dist: pydantic==2.5.2
Requires-Dist: rapidfuzz==3.5.2
Requires-Dist: rich==13.7.0
Requires-Dist: scholarly==1.7.11
